setup.py
ldjcourse/__init__.py
ldjcourse.egg-info/PKG-INFO
ldjcourse.egg-info/SOURCES.txt
ldjcourse.egg-info/dependency_links.txt
ldjcourse.egg-info/top_level.txt
ldjcourse/assist/__init__.py
ldjcourse/assist/a1/__init__.py
ldjcourse/assist/a1/case1_v1.py
ldjcourse/assist/a1/case2_v1.py
ldjcourse/assist/a1/case3_v1.py
ldjcourse/assist/a1/case4_v1.py
ldjcourse/assist/a1/case5_v1.py
ldjcourse/assist/a1/case6_v1.py
ldjcourse/assist/b1/__init__.py
ldjcourse/assist/b1/case1_v1.py
ldjcourse/settings/__init__.py
ldjcourse/settings/settings_client.py
ldjcourse/settings/settings_server.py