Metadata-Version: 2.1
Name: ldjcourse
Version: 0.0.8.6
Summary: 本安装包由元蓝先生为教学专门构建，提供教学所需的工具和资源。元蓝先生活跃于B站，分享编程、数据分析和人工智能相关教学内容。链接：https://space.bilibili.com/3546564903569609
Author: B站 元蓝先生
License: MIT
